azure/storage/blob/__init__.py
azure/storage/blob/_blob_client.py
azure/storage/blob/_blob_client_helpers.py
azure/storage/blob/_blob_service_client.py
azure/storage/blob/_blob_service_client_helpers.py
azure/storage/blob/_container_client.py
azure/storage/blob/_container_client_helpers.py
azure/storage/blob/_deserialize.py
azure/storage/blob/_download.py
azure/storage/blob/_encryption.py
azure/storage/blob/_lease.py
azure/storage/blob/_list_blobs_helper.py
azure/storage/blob/_models.py
azure/storage/blob/_quick_query_helper.py
azure/storage/blob/_serialize.py
azure/storage/blob/_shared_access_signature.py
azure/storage/blob/_upload_helpers.py
azure/storage/blob/_version.py
azure/storage/blob/py.typed
azure/storage/blob/_generated/__init__.py
azure/storage/blob/_generated/_azure_blob_storage.py
azure/storage/blob/_generated/_configuration.py
azure/storage/blob/_generated/_patch.py
azure/storage/blob/_generated/_serialization.py
azure/storage/blob/_generated/py.typed
azure/storage/blob/_generated/aio/__init__.py
azure/storage/blob/_generated/aio/_azure_blob_storage.py
azure/storage/blob/_generated/aio/_configuration.py
azure/storage/blob/_generated/aio/_patch.py
azure/storage/blob/_generated/aio/operations/__init__.py
azure/storage/blob/_generated/aio/operations/_append_blob_operations.py
azure/storage/blob/_generated/aio/operations/_blob_operations.py
azure/storage/blob/_generated/aio/operations/_block_blob_operations.py
azure/storage/blob/_generated/aio/operations/_container_operations.py
azure/storage/blob/_generated/aio/operations/_page_blob_operations.py
azure/storage/blob/_generated/aio/operations/_patch.py
azure/storage/blob/_generated/aio/operations/_service_operations.py
azure/storage/blob/_generated/models/__init__.py
azure/storage/blob/_generated/models/_azure_blob_storage_enums.py
azure/storage/blob/_generated/models/_models_py3.py
azure/storage/blob/_generated/models/_patch.py
azure/storage/blob/_generated/operations/__init__.py
azure_storage_blob-12.25.0.dist-info/LICENSE
azure_storage_blob-12.25.0.dist-info/METADATA
azure_storage_blob-12.25.0.dist-info/WHEEL
azure_storage_blob-12.25.0.dist-info/top_level.txt
azure_storage_blob-12.25.0.dist-info/RECORD
